.DS_Store
many_world/__init__.py
many_world/base_envs.py
many_world/many_world.py
many_world/mujoco_env.py
many_world/__pycache__/__init__.cpython-36.pyc
many_world/__pycache__/base_envs.cpython-36.pyc
many_world/__pycache__/many_world.cpython-36.pyc
many_world/__pycache__/mujoco_env.cpython-36.pyc
many_world/assets/2-link-arm.xml
many_world/assets/bordered-arena.xml
many_world/assets/c-maze-arena-nc.xml
many_world/assets/c-maze-arena.xml
many_world/assets/c-maze-no-collision.xml
many_world/assets/c-maze.xml
many_world/assets/four-room-arena.xml
many_world/assets/four-room.xml
many_world/assets/h-maze-arena-open.xml
many_world/assets/h-maze-arena.xml
many_world/assets/h-maze-open.xml
many_world/assets/h-maze.xml
many_world/assets/lighting.xml
many_world/assets/many-world-1.xml
many_world/assets/many-world-2.xml
many_world/assets/many-world-3.xml
many_world/assets/many-world-4.xml
many_world/assets/peg-2d-arena.xml
many_world/assets/peg-2d.xml
many_world/assets/pendulum-lighting.xml
many_world/assets/pendulum.xml
many_world/assets/point-mass-multitask-2.xml
many_world/assets/point-mass-multitask-4.xml
many_world/assets/point-mass-quadrangle.xml
many_world/assets/point-mass.xml
many_world/assets/reacher-multitask-2.xml
many_world/assets/reacher-multitask-3.xml
many_world/assets/reacher-multitask-4.xml
many_world/assets/reacher-single-task.xml
many_world/assets/回-maze-arena.xml
many_world/assets/回-maze.xml
many_world-0.0.6.dist-info/METADATA
many_world-0.0.6.dist-info/WHEEL
many_world-0.0.6.dist-info/top_level.txt
many_world-0.0.6.dist-info/RECORD
